exacting-0.2.0.dist-info/METADATA
exacting-0.2.0.dist-info/WHEEL
exacting-0.2.0.dist-info/licenses/LICENSE
exacting.libs/libgcc_s-5b5488a6.so.1
exacting/__init__.py
exacting/core.py
exacting/exacting.pyi
exacting/exacting.pypy39-pp73-arm-linux-gnu.so
exacting/fields.py
exacting/result.py
exacting/types.py
exacting/utils.py
exacting/validator_map.py
exacting/validators.py
exacting-0.2.0.dist-info/RECORD
